nestednop/LICENSE
nestednop/README.MD
nestednop/__init__.py
nestednop/requirements.txt
nestednop/thirdparty.json
nestednop-0.1.dist-info/LICENSE.rst
nestednop-0.1.dist-info/METADATA
nestednop-0.1.dist-info/WHEEL
nestednop-0.1.dist-info/top_level.txt
nestednop-0.1.dist-info/RECORD
